MANIFEST.in
README.txt
distribute_setup.py
setup.py
docs/build/html/command_ref.html
docs/build/html/developers.html
docs/build/html/genindex.html
docs/build/html/history.html
docs/build/html/index.html
docs/build/html/install.html
docs/build/html/search.html
docs/build/html/searchindex.js
docs/build/html/_sources/command_ref.txt
docs/build/html/_sources/developers.txt
docs/build/html/_sources/history.txt
docs/build/html/_sources/index.txt
docs/build/html/_sources/install.txt
docs/build/html/_static/basic.css
docs/build/html/_static/default.css
docs/build/html/_static/doctools.js
docs/build/html/_static/file.png
docs/build/html/_static/jquery.js
docs/build/html/_static/minus.png
docs/build/html/_static/nature.css
docs/build/html/_static/plus.png
docs/build/html/_static/pygments.css
docs/build/html/_static/searchtools.js
docs/build/html/_static/sidebar.js
docs/build/html/_static/underscore.js
docs/source/command_ref.rst
docs/source/conf.py
docs/source/developers.rst
docs/source/history.rst
docs/source/index.rst
docs/source/install.rst
tests/run_tests
tests/shunit2
tests/test_mktmpenv.sh
tests/util.sh
virtualenvwrapper/__init__.py
virtualenvwrapper/tmpenv.py
virtualenvwrapper/tmpenv.sh
virtualenvwrapper.tmpenv.egg-info/PKG-INFO
virtualenvwrapper.tmpenv.egg-info/SOURCES.txt
virtualenvwrapper.tmpenv.egg-info/dependency_links.txt
virtualenvwrapper.tmpenv.egg-info/entry_points.txt
virtualenvwrapper.tmpenv.egg-info/namespace_packages.txt
virtualenvwrapper.tmpenv.egg-info/not-zip-safe
virtualenvwrapper.tmpenv.egg-info/requires.txt
virtualenvwrapper.tmpenv.egg-info/top_level.txt