Metadata-Version: 1.1
Name: virtualenvwrapper.tmpenv
Version: 1.0
Summary: Temporary virtualenvs are automatically deleted when deactivated
Home-page: http://www.doughellmann.com/projects/virtualenvwrapper.tmpenv/
Author: Doug Hellmann
Author-email: doug.hellmann@gmail.com
License: UNKNOWN
Platform: Any
Classifier: Development Status :: 5 - Production/Stable
Classifier: License :: OSI Approved :: BSD License
Classifier: Programming Language :: Python
Classifier: Programming Language :: Python :: 2
Classifier: Programming Language :: Python :: 2.4
Classifier: Programming Language :: Python :: 2.5
Classifier: Programming Language :: Python :: 2.6
Classifier: Programming Language :: Python :: 2.7
Classifier: Intended Audience :: Developers
Classifier: Environment :: Console
Provides: virtualenvwrapper
Provides: virtualenvwrapper.tmpenv
